[{"id":899,"name":"名探偵コナン","name_cn":"名侦探柯南","air_date":"1996-01-08","weekDayJP":1,"weekDayCN":4,"timeJP":"1800","timeCN":"1815","image":"http://lain.bgm.tv/pic/cover/g/01/88/899_Q3F3X.jpg","eps":[{"id":828535,"url":"http://bgm.tv/ep/828535","type":0,"sort":943,"name":"東京婆ールズコレクション","name_cn":"","airdate":"2019-06-15","status":"Air"},{"id":828536,"url":"http://bgm.tv/ep/828536","type":0,"sort":944,"name":"いいね。の代償(前編)","name_cn":"","airdate":"2019-06-22","status":"NA"},{"id":828537,"url":"http://bgm.tv/ep/828537","type":0,"sort":945,"name":"いいね。の代償(後編)","name_cn":"","airdate":"2019-06-29","status":"NA"}]},
{"id":975,"name":"ONE PIECE","name_cn":"海贼王","air_date":"1999-10-20","weekDayJP":3,"weekDayCN":0,"timeJP":"0930","timeCN":"0930","image":"http://lain.bgm.tv/pic/cover/g/92/97/975_YKuWd.jpg","eps":[{"id":881792,"url":"http://bgm.tv/ep/881792","type":0,"sort":889,"name":"","name_cn":"","airdate":"2019-06-16","status":"Air"},{"id":881793,"url":"http://bgm.tv/ep/881793","type":0,"sort":890,"name":"","name_cn":"","airdate":"2019-06-23","status":"NA"}]},
{"id":161845,"name":"ぼのぼの","name_cn":"暖暖日记","air_date":"2016-04-02","weekDayJP":6,"weekDayCN":6,"timeJP":"0352","timeCN":"0800","image":"http://lain.bgm.tv/pic/cover/g/a3/bc/161845_r4UfV.jpg","eps":[{"id":860204,"url":"http://bgm.tv/ep/860204","type":0,"sort":165,"name":"アソビちゃんと遊ぼう","name_cn":"和小玩玩耍吧","airdate":"2019-06-15","status":"Air"},{"id":860205,"url":"http://bgm.tv/ep/860205","type":0,"sort":166,"name":"","name_cn":"","airdate":"2019-06-22","status":"NA"},{"id":860206,"url":"http://bgm.tv/ep/860206","type":0,"sort":167,"name":"","name_cn":"","airdate":"2019-06-29","status":"NA"}]},
{"id":192680,"name":"ポケットモンスター サン＆ムーン","name_cn":"精灵宝可梦 太阳&amp;月亮","air_date":"2016-11-17","weekDayJP":4,"weekDayCN":2,"timeJP":"1855","timeCN":"0001","image":"http://lain.bgm.tv/pic/cover/g/8c/a3/192680_IXRMh.jpg","eps":[{"id":873875,"url":"http://bgm.tv/ep/873875","type":0,"sort":126,"name":"ピカチュウのドキドキ探検隊！","name_cn":"皮卡丘的心动探险队！","airdate":"2019-06-16","status":"Air"},{"id":873876,"url":"http://bgm.tv/ep/873876","type":0,"sort":127,"name":"グラジオとリーリエ！父の幻影を追って！！","name_cn":"格拉吉欧与莉莉艾！追寻父亲的幻影!!","airdate":"2019-06-23","status":"NA"}]},
{"id":202661,"name":"BORUTO-ボルト- NARUTO NEXT GENERATIONS","name_cn":"火影忍者 博人传之火影次世代","air_date":"2017-04-05","weekDayJP":3,"weekDayCN":0,"timeJP":"1655","timeCN":"1730","image":"http://lain.bgm.tv/pic/cover/g/70/65/202661_Xx5X3.jpg","eps":[{"id":873850,"url":"http://bgm.tv/ep/873850","type":0,"sort":111,"name":"湯煙忍法帖・ミライの玉!!","name_cn":"汤烟忍法帖·未来之玉!!","airdate":"2019-06-16","status":"Air"},{"id":873851,"url":"http://bgm.tv/ep/873851","type":0,"sort":112,"name":"中忍昇格首脳会議","name_cn":"","airdate":"2019-06-23","status":"NA"}]},
{"id":202615,"name":"遊☆戯☆王VRAINS","name_cn":"游戏王VRAINS","air_date":"2017-05-10","weekDayJP":3,"weekDayCN":0,"timeJP":"1725","timeCN":"","image":"http://lain.bgm.tv/pic/cover/g/5f/78/202615_11QWz.jpg","eps":[{"id":879065,"url":"http://bgm.tv/ep/879065","type":0,"sort":106,"name":"がんばれ!!ロボッピ","name_cn":"","airdate":"2019-06-12","status":"Air"},{"id":879066,"url":"http://bgm.tv/ep/879066","type":0,"sort":107,"name":"鬼を討つ","name_cn":"","airdate":"2019-06-19","status":"Air"},{"id":879067,"url":"http://bgm.tv/ep/879067","type":0,"sort":108,"name":"","name_cn":"","airdate":"2019-06-26","status":"NA"}]},
{"id":227240,"name":"新幹線変形ロボ シンカリオン","name_cn":"新干线变形机器人","air_date":"2018-01-06","weekDayJP":6,"weekDayCN":6,"timeJP":"0600","timeCN":"0000","image":"http://lain.bgm.tv/pic/cover/g/9e/8a/227240_ere7e.jpg","eps":[{"id":873597,"url":"http://bgm.tv/ep/873597","type":0,"sort":74,"name":"","name_cn":"","airdate":"2019-06-15","status":"Air"},{"id":873598,"url":"http://bgm.tv/ep/873598","type":0,"sort":75,"name":"","name_cn":"","airdate":"2019-06-22","status":"NA"},{"id":873599,"url":"http://bgm.tv/ep/873599","type":0,"sort":76,"name":"","name_cn":"","airdate":"2019-06-29","status":"NA"}]},
{"id":234531,"name":"ゲゲゲの鬼太郎","name_cn":"鬼太郎 第六季","air_date":"2018-04-01","weekDayJP":0,"weekDayCN":0,"timeJP":"0800","timeCN":"1124","image":"http://lain.bgm.tv/pic/cover/g/30/71/234531_u3ujU.jpg","eps":[{"id":876026,"url":"http://bgm.tv/ep/876026","type":0,"sort":60,"name":"","name_cn":"","airdate":"2019-06-16","status":"Air"},{"id":876027,"url":"http://bgm.tv/ep/876027","type":0,"sort":61,"name":"","name_cn":"","airdate":"2019-06-23","status":"NA"}]},
{"id":248907,"name":"キラキラハッピー★ ひらけ！ここたま","name_cn":"闪亮幸福★开启吧!心灵","air_date":"2018-09-06","weekDayJP":4,"weekDayCN":0,"timeJP":"1655","timeCN":"","image":"http://lain.bgm.tv/pic/cover/g/55/48/248907_qQu4P.jpg","eps":[{"id":859017,"url":"http://bgm.tv/ep/859017","type":0,"sort":40,"name":"","name_cn":"","airdate":"2019-06-13","status":"Air"},{"id":859018,"url":"http://bgm.tv/ep/859018","type":0,"sort":41,"name":"","name_cn":"","airdate":"2019-06-20","status":"Today"},{"id":859019,"url":"http://bgm.tv/ep/859019","type":0,"sort":42,"name":"","name_cn":"","airdate":"2019-06-27","status":"NA"}]},
{"id":235128,"name":"ジョジョの奇妙な冒険 黄金の風","name_cn":"JOJO的奇妙冒险 黄金之风","air_date":"2018-10-05","weekDayJP":6,"weekDayCN":6,"timeJP":"0005","timeCN":"0135","image":"http://lain.bgm.tv/pic/cover/g/42/29/235128_MLxi3.jpg","eps":[{"id":830046,"url":"http://bgm.tv/ep/830046","type":0,"sort":34,"name":"鎮魂歌は静かに奏でられる その①","name_cn":"镇魂歌沉静地演奏着 其一","airdate":"2019-06-14","status":"Air"},{"id":830047,"url":"http://bgm.tv/ep/830047","type":0,"sort":35,"name":"鎮魂歌は静かに奏でられる その②","name_cn":"镇魂歌沉静地演奏着 其二","airdate":"2019-06-21","status":"NA"},{"id":830048,"url":"http://bgm.tv/ep/830048","type":0,"sort":36,"name":"","name_cn":"","airdate":"2019-06-28","status":"NA"}]},
{"id":239974,"name":"からくりサーカス","name_cn":"魔偶马戏团","air_date":"2018-10-11","weekDayJP":4,"weekDayCN":3,"timeJP":"2130","timeCN":"2300","image":"http://lain.bgm.tv/pic/cover/g/87/0c/239974_5p130.jpg","eps":[{"id":785362,"url":"http://bgm.tv/ep/785362","type":0,"sort":34,"name":"背中を守る者","name_cn":"","airdate":"2019-06-13","status":"Air"},{"id":785363,"url":"http://bgm.tv/ep/785363","type":0,"sort":35,"name":"抱擁","name_cn":"","airdate":"2019-06-20","status":"Today"},{"id":785364,"url":"http://bgm.tv/ep/785364","type":0,"sort":36,"name":"","name_cn":"","airdate":"2019-06-27","status":"NA"}]},
{"id":259877,"name":"イナズマイレブン オリオンの刻印","name_cn":"闪电十一人 俄里翁的刻印","air_date":"2018-10-05","weekDayJP":5,"weekDayCN":0,"timeJP":"1655","timeCN":"","image":"http://lain.bgm.tv/pic/cover/g/11/3e/259877_1kH8s.jpg","eps":[{"id":886596,"url":"http://bgm.tv/ep/886596","type":0,"sort":34,"name":"衝撃の追加メンバー","name_cn":"","airdate":"2019-06-14","status":"Air"},{"id":886597,"url":"http://bgm.tv/ep/886597","type":0,"sort":35,"name":"華麗なフロイ","name_cn":"","airdate":"2019-06-21","status":"NA"},{"id":886598,"url":"http://bgm.tv/ep/886598","type":0,"sort":36,"name":"","name_cn":"","airdate":"2019-06-28","status":"NA"}]},
{"id":174186,"name":"FAIRY TAIL ファイナルシリーズ","name_cn":"妖精的尾巴 最终季","air_date":"2018-10-07","weekDayJP":0,"weekDayCN":0,"timeJP":"0600","timeCN":"0730","image":"http://lain.bgm.tv/pic/cover/g/67/b7/174186_4S505.jpg","eps":[{"id":873863,"url":"http://bgm.tv/ep/873863","type":0,"sort":313,"name":"","name_cn":"","airdate":"2019-06-16","status":"Air"},{"id":873864,"url":"http://bgm.tv/ep/873864","type":0,"sort":314,"name":"","name_cn":"","airdate":"2019-06-23","status":"NA"}]},
{"id":263322,"name":"愛玩怪獣","name_cn":"爱玩怪兽","air_date":"2018-10-07","weekDayJP":1,"weekDayCN":1,"timeJP":"0000","timeCN":"0000","image":"http://lain.bgm.tv/pic/cover/g/72/97/263322_wEMzJ.jpg","eps":[{"id":834111,"url":"http://bgm.tv/ep/834111","type":0,"sort":36,"name":"オオアバレ","name_cn":"大闹","airdate":"2019-06-16","status":"Air"},{"id":834112,"url":"http://bgm.tv/ep/834112","type":0,"sort":37,"name":"","name_cn":"","airdate":"2019-06-23","status":"NA"}]},
{"id":217660,"name":"盾の勇者の成り上がり","name_cn":"盾之勇者成名录","air_date":"2019-01-09","weekDayJP":4,"weekDayCN":3,"timeJP":"0005","timeCN":"2300","image":"http://lain.bgm.tv/pic/cover/g/b9/9b/217660_6BBp6.jpg","eps":[{"id":851548,"url":"http://bgm.tv/ep/851548","type":0,"sort":23,"name":"カルミラ島","name_cn":"卡尔米拉岛","airdate":"2019-06-12","status":"Air"},{"id":851549,"url":"http://bgm.tv/ep/851549","type":0,"sort":24,"name":"異世界の守護者","name_cn":"异世界的守护者","airdate":"2019-06-19","status":"Air"},{"id":851550,"url":"http://bgm.tv/ep/851550","type":0,"sort":25,"name":"","name_cn":"","airdate":"2019-06-26","status":"NA"}]},
{"id":240838,"name":"どろろ","name_cn":"多罗罗","air_date":"2019-01-07","weekDayJP":1,"weekDayCN":1,"timeJP":"2100","timeCN":"2200","image":"http://lain.bgm.tv/pic/cover/g/d3/da/240838_5Ax95.jpg","eps":[{"id":851361,"url":"http://bgm.tv/ep/851361","type":0,"sort":22,"name":"縫の巻","name_cn":"缝之卷","airdate":"2019-06-10","status":"Air"},{"id":851362,"url":"http://bgm.tv/ep/851362","type":0,"sort":23,"name":"鬼神の巻","name_cn":"鬼神之卷","airdate":"2019-06-17","status":"Air"},{"id":851363,"url":"http://bgm.tv/ep/851363","type":0,"sort":24,"name":"","name_cn":"","airdate":"2019-06-23","status":"NA"}]},
{"id":264588,"name":"スター☆トゥインクル プリキュア","name_cn":"星光☆闪亮 光之美少女","air_date":"2019-02-03","weekDayJP":0,"weekDayCN":0,"timeJP":"0730","timeCN":"1132","image":"http://lain.bgm.tv/pic/cover/g/09/56/264588_X7RM5.jpg","eps":[{"id":856713,"url":"http://bgm.tv/ep/856713","type":0,"sort":20,"name":"銀河に光る☆キュアコスモ誕生！","name_cn":"","airdate":"2019-06-23","status":"NA"},{"id":856714,"url":"http://bgm.tv/ep/856714","type":0,"sort":21,"name":"","name_cn":"","airdate":"2019-06-29","status":"NA"}]},
{"id":272921,"name":"アイカツフレンズ！～かがやきのジュエル～","name_cn":"偶像活动Friends～闪耀的宝石～","air_date":"2019-04-04","weekDayJP":4,"weekDayCN":4,"timeJP":"1725","timeCN":"1830","image":"http://lain.bgm.tv/pic/cover/g/e2/ed/272921_Wkee1.jpg","eps":[{"id":872959,"url":"http://bgm.tv/ep/872959","type":0,"sort":61,"name":"","name_cn":"","airdate":"2019-06-13","status":"Air"},{"id":872960,"url":"http://bgm.tv/ep/872960","type":0,"sort":62,"name":"","name_cn":"","airdate":"2019-06-20","status":"Today"},{"id":872961,"url":"http://bgm.tv/ep/872961","type":0,"sort":63,"name":"","name_cn":"","airdate":"2019-06-27","status":"NA"}]},
{"id":226256,"name":"賢者の孫","name_cn":"贤者之孙","air_date":"2019-04-10","weekDayJP":3,"weekDayCN":3,"timeJP":"2230","timeCN":"2330","image":"http://lain.bgm.tv/pic/cover/g/dc/81/226256_dZdQ2.jpg","eps":[{"id":874382,"url":"http://bgm.tv/ep/874382","type":0,"sort":10,"name":"滅亡する帝国","name_cn":"灭亡的帝国","airdate":"2019-06-12","status":"Air"},{"id":874383,"url":"http://bgm.tv/ep/874383","type":0,"sort":11,"name":"史上最強の魔法師集団","name_cn":"","airdate":"2019-06-19","status":"Air"},{"id":874384,"url":"http://bgm.tv/ep/874384","type":0,"sort":12,"name":"そして、世界へ…","name_cn":"","airdate":"2019-06-26","status":"NA"}]},
{"id":257369,"name":"ぼくたちは勉強ができない","name_cn":"我们真的学不来","air_date":"2019-04-06","weekDayJP":6,"weekDayCN":0,"timeJP":"2330","timeCN":"0100","image":"http://lain.bgm.tv/pic/cover/g/21/a6/257369_GEgqd.jpg","eps":[{"id":874143,"url":"http://bgm.tv/ep/874143","type":0,"sort":11,"name":"威厳ある先任者は時に[Ｘ]にかしづく","name_cn":"威严的前任有时会服侍[Ｘ]","airdate":"2019-06-15","status":"Air"},{"id":874144,"url":"http://bgm.tv/ep/874144","type":0,"sort":12,"name":"天才は時に[Ｘ]をともに分かち追懐する","name_cn":"天才有时会与[Ｘ]共同追忆","airdate":"2019-06-22","status":"NA"}]},
{"id":249245,"name":"KING OF PRISM -Shiny Seven Stars-","name_cn":"","air_date":"2019-04-08","weekDayJP":2,"weekDayCN":0,"timeJP":"0035","timeCN":"","image":"http://lain.bgm.tv/pic/cover/g/06/53/249245_wBXfw.jpg","eps":[{"id":800768,"url":"http://bgm.tv/ep/800768","type":0,"sort":9,"name":"大和アレクサンダー THE CHARISMA OF STREET","name_cn":"大和亚历山大 街舞教主","airdate":"2019-06-10","status":"Air"},{"id":800769,"url":"http://bgm.tv/ep/800769","type":0,"sort":10,"name":"如月ルヰ プリズムの使者","name_cn":"如月琉铱 Prism的使者","airdate":"2019-06-17","status":"Air"},{"id":800770,"url":"http://bgm.tv/ep/800770","type":0,"sort":11,"name":"","name_cn":"","airdate":"2019-06-24","status":"NA"}]},
{"id":262111,"name":"なんでここに先生が!?","name_cn":"为什么老师会在这里！？","air_date":"2019-04-07","weekDayJP":1,"weekDayCN":0,"timeJP":"0005","timeCN":"","image":"http://lain.bgm.tv/pic/cover/g/ef/65/262111_wIH5f.jpg","eps":[{"id":874443,"url":"http://bgm.tv/ep/874443","type":0,"sort":11,"name":"海水欲／挿入洞","name_cn":"","airdate":"2019-06-16","status":"Air"},{"id":874444,"url":"http://bgm.tv/ep/874444","type":0,"sort":12,"name":"","name_cn":"","airdate":"2019-06-23","status":"NA"}]},
{"id":262865,"name":"異世界かるてっと","name_cn":"异世界四重奏","air_date":"2019-04-09","weekDayJP":2,"weekDayCN":2,"timeJP":"2330","timeCN":"2330","image":"http://lain.bgm.tv/pic/cover/g/c0/e9/262865_HzIiM.jpg","eps":[{"id":874358,"url":"http://bgm.tv/ep/874358","type":0,"sort":10,"name":"参戦！らいばるたち","name_cn":"参战！对手们登场","airdate":"2019-06-11","status":"Air"},{"id":874359,"url":"http://bgm.tv/ep/874359","type":0,"sort":11,"name":"","name_cn":"","airdate":"2019-06-18","status":"Air"},{"id":874360,"url":"http://bgm.tv/ep/874360","type":0,"sort":12,"name":"","name_cn":"","airdate":"2019-06-25","status":"NA"}]},
{"id":241335,"name":"ひとりぼっちの○○生活","name_cn":"一个人的○○小日子","air_date":"2019-04-05","weekDayJP":6,"weekDayCN":6,"timeJP":"0125","timeCN":"0255","image":"http://lain.bgm.tv/pic/cover/g/9f/ab/241335_sLGll.jpg","eps":[{"id":874079,"url":"http://bgm.tv/ep/874079","type":0,"sort":11,"name":"たぷたぷからぷりぷりまで","name_cn":"","airdate":"2019-06-14","status":"Air"},{"id":874080,"url":"http://bgm.tv/ep/874080","type":0,"sort":12,"name":"","name_cn":"","airdate":"2019-06-21","status":"NA"}]},
{"id":268510,"name":"川柳少女","name_cn":"川柳少女","air_date":"2019-04-05","weekDayJP":6,"weekDayCN":6,"timeJP":"0055","timeCN":"0210","image":"http://lain.bgm.tv/pic/cover/g/b4/fb/268510_XKKrF.jpg","eps":[{"id":874052,"url":"http://bgm.tv/ep/874052","type":0,"sort":11,"name":"あなたと花火を","name_cn":"与你去看烟花","airdate":"2019-06-14","status":"Air"},{"id":874053,"url":"http://bgm.tv/ep/874053","type":0,"sort":12,"name":"七々子とエイジ","name_cn":"","airdate":"2019-06-21","status":"NA"}]},
{"id":268412,"name":"みだらな青ちゃんは勉強ができない","name_cn":"淫乱的青酱不能学习","air_date":"2019-04-05","weekDayJP":6,"weekDayCN":0,"timeJP":"0110","timeCN":"0225","image":"http://lain.bgm.tv/pic/cover/g/7d/87/268412_P63Pf.jpg","eps":[{"id":874064,"url":"http://bgm.tv/ep/874064","type":0,"sort":11,"name":"青ちゃんはツルツルパンツがはけない","name_cn":"小青穿不了光滑的内裤","airdate":"2019-06-14","status":"Air"},{"id":874065,"url":"http://bgm.tv/ep/874065","type":0,"sort":12,"name":"青ちゃんは勉強ができない","name_cn":"小青无法用功念书","airdate":"2019-06-21","status":"NA"}]},
{"id":266455,"name":"フルーツバスケット 1st Season","name_cn":"水果篮子 第一季","air_date":"2019-04-05","weekDayJP":6,"weekDayCN":6,"timeJP":"0023","timeCN":"0123","image":"http://lain.bgm.tv/pic/cover/g/20/f2/266455_fRBdM.jpg","eps":[{"id":874067,"url":"http://bgm.tv/ep/874067","type":0,"sort":11,"name":"とってもステキなお宿です","name_cn":"这间旅馆非常棒","airdate":"2019-06-14","status":"Air"},{"id":874068,"url":"http://bgm.tv/ep/874068","type":0,"sort":12,"name":"楽しそうだね","name_cn":"看起来很开心啊","airdate":"2019-06-21","status":"NA"},{"id":880603,"url":"http://bgm.tv/ep/880603","type":0,"sort":13,"name":"","name_cn":"","airdate":"2019-06-28","status":"NA"}]},
{"id":268165,"name":"世話やきキツネの仙狐さん","name_cn":"贤惠幼妻仙狐小姐","air_date":"2019-04-10","weekDayJP":3,"weekDayCN":3,"timeJP":"2130","timeCN":"2300","image":"http://lain.bgm.tv/pic/cover/g/57/96/268165_qOQsQ.jpg","eps":[{"id":873087,"url":"http://bgm.tv/ep/873087","type":0,"sort":10,"name":"たまには童心に返るのもよいじゃろ？","name_cn":"偶尔回归童心也不错的吧？","airdate":"2019-06-12","status":"Air"},{"id":873088,"url":"http://bgm.tv/ep/873088","type":0,"sort":11,"name":"","name_cn":"","airdate":"2019-06-19","status":"Air"},{"id":873089,"url":"http://bgm.tv/ep/873089","type":0,"sort":12,"name":"","name_cn":"","airdate":"2019-06-26","status":"NA"}]},
{"id":204135,"name":"この世の果てで恋を唄う少女YU-NO","name_cn":"在世界尽头咏唱恋曲的少女YU-NO","air_date":"2019-04-02","weekDayJP":2,"weekDayCN":2,"timeJP":"2200","timeCN":"2200","image":"http://lain.bgm.tv/pic/cover/g/66/f5/204135_Y6yi3.jpg","eps":[{"id":840237,"url":"http://bgm.tv/ep/840237","type":0,"sort":11,"name":"もう一度あのキスを","name_cn":"重演那一天的吻","airdate":"2019-06-11","status":"Air"},{"id":840238,"url":"http://bgm.tv/ep/840238","type":0,"sort":12,"name":"白衣の下の秘密","name_cn":"白衣之下的秘密","airdate":"2019-06-18","status":"Air"},{"id":840239,"url":"http://bgm.tv/ep/840239","type":0,"sort":13,"name":"","name_cn":"","airdate":"2019-06-25","status":"NA"}]},
{"id":247886,"name":"消滅都市","name_cn":"消灭都市","air_date":"2019-04-07","weekDayJP":0,"weekDayCN":0,"timeJP":"2230","timeCN":"2330","image":"http://lain.bgm.tv/pic/cover/g/3a/46/247886_2HP7z.jpg","eps":[{"id":874290,"url":"http://bgm.tv/ep/874290","type":0,"sort":11,"name":"信頼","name_cn":"","airdate":"2019-06-16","status":"Air"},{"id":874291,"url":"http://bgm.tv/ep/874291","type":0,"sort":12,"name":"未来","name_cn":"","airdate":"2019-06-23","status":"NA"}]},
{"id":245665,"name":"鬼滅の刃","name_cn":"鬼灭之刃","air_date":"2019-04-06","weekDayJP":6,"weekDayCN":0,"timeJP":"2230","timeCN":"0000","image":"http://lain.bgm.tv/pic/cover/g/9d/d1/245665_5an54.jpg","eps":[{"id":858667,"url":"http://bgm.tv/ep/858667","type":0,"sort":11,"name":"鼓の屋敷","name_cn":"鼓之宅邸","airdate":"2019-06-15","status":"Air"},{"id":858668,"url":"http://bgm.tv/ep/858668","type":0,"sort":12,"name":"","name_cn":"","airdate":"2019-06-22","status":"NA"},{"id":880824,"url":"http://bgm.tv/ep/880824","type":0,"sort":13,"name":"","name_cn":"","airdate":"2019-06-29","status":"NA"}]},
{"id":268320,"name":"アイドルマスター シンデレラガールズ劇場 CLIMAX SEASON","name_cn":"偶像大师 灰姑娘女孩剧场 高潮季","air_date":"2019-04-02","weekDayJP":2,"weekDayCN":2,"timeJP":"2054","timeCN":"2154","image":"http://lain.bgm.tv/pic/cover/g/f2/28/268320_wRhYU.jpg","eps":[{"id":873956,"url":"http://bgm.tv/ep/873956","type":0,"sort":50,"name":"その先の風を／まるで宇宙の星々／大賢者の修羅場・リリーフは…これ！","name_cn":"前方的风/如同宇宙星辰/大贤者的修罗场·救援就用 这个","airdate":"2019-06-11","status":"Air"},{"id":873957,"url":"http://bgm.tv/ep/873957","type":0,"sort":51,"name":"","name_cn":"","airdate":"2019-06-18","status":"Air"}]},
{"id":260373,"name":"超可動ガール1/6","name_cn":"超可动女孩1/6","air_date":"2019-04-06","weekDayJP":1,"weekDayCN":0,"timeJP":"2300","timeCN":"","image":"http://lain.bgm.tv/pic/cover/g/b9/55/260373_2Z2oz.jpg","eps":[{"id":874455,"url":"http://bgm.tv/ep/874455","type":0,"sort":11,"name":"","name_cn":"","airdate":"2019-06-15","status":"Air"},{"id":874456,"url":"http://bgm.tv/ep/874456","type":0,"sort":12,"name":"","name_cn":"","airdate":"2019-06-22","status":"NA"}]},
{"id":260371,"name":"女子かう生","name_cn":"女子高中生","air_date":"2019-04-06","weekDayJP":6,"weekDayCN":0,"timeJP":"2215","timeCN":"","image":"http://lain.bgm.tv/pic/cover/g/81/26/260371_E1a69.jpg","eps":[{"id":874467,"url":"http://bgm.tv/ep/874467","type":0,"sort":11,"name":"女子かう生とコタツ","name_cn":"女子高中生与被炉","airdate":"2019-06-15","status":"Air"},{"id":874468,"url":"http://bgm.tv/ep/874468","type":0,"sort":12,"name":"","name_cn":"","airdate":"2019-06-22","status":"NA"}]},
{"id":269075,"name":"ノブナガ先生の幼な妻","name_cn":"信长老师的年幼妻子","air_date":"2019-04-06","weekDayJP":6,"weekDayCN":0,"timeJP":"2220","timeCN":"","image":"http://lain.bgm.tv/pic/cover/g/3e/19/269075_h9c34.jpg","eps":[{"id":874323,"url":"http://bgm.tv/ep/874323","type":0,"sort":11,"name":"慈徳院とお鍋の方の望み","name_cn":"","airdate":"2019-06-15","status":"Air"},{"id":874324,"url":"http://bgm.tv/ep/874324","type":0,"sort":12,"name":"","name_cn":"","airdate":"2019-06-22","status":"NA"}]},
{"id":272475,"name":"Fairy gone フェアリーゴーン","name_cn":"Fairy gone","air_date":"2019-04-07","weekDayJP":0,"weekDayCN":0,"timeJP":"2300","timeCN":"","image":"http://lain.bgm.tv/pic/cover/g/39/23/272475_k60P6.jpg","eps":[{"id":874254,"url":"http://bgm.tv/ep/874254","type":0,"sort":11,"name":"招かざる音楽隊","name_cn":"不请自来的乐团","airdate":"2019-06-16","status":"Air"},{"id":874255,"url":"http://bgm.tv/ep/874255","type":0,"sort":12,"name":"","name_cn":"","airdate":"2019-06-23","status":"NA"}]},
{"id":267250,"name":"RobiHachi","name_cn":"","air_date":"2019-04-08","weekDayJP":1,"weekDayCN":1,"timeJP":"2230","timeCN":"2330","image":"http://lain.bgm.tv/pic/cover/g/f2/be/267250_cMvqQ.jpg","eps":[{"id":874334,"url":"http://bgm.tv/ep/874334","type":0,"sort":10,"name":"相棒喧嘩は犬も喰わない","name_cn":"搭档吵架狗都懒得理","airdate":"2019-06-10","status":"Air"},{"id":874335,"url":"http://bgm.tv/ep/874335","type":0,"sort":11,"name":"","name_cn":"","airdate":"2019-06-17","status":"Air"},{"id":874336,"url":"http://bgm.tv/ep/874336","type":0,"sort":12,"name":"","name_cn":"","airdate":"2019-06-24","status":"NA"}]},
{"id":261048,"name":"叛逆性ミリオンアーサー 第2シーズン","name_cn":"叛逆性百万亚瑟王 第二季","air_date":"2019-04-04","weekDayJP":4,"weekDayCN":4,"timeJP":"2100","timeCN":"2100","image":"http://lain.bgm.tv/pic/cover/g/77/c0/261048_w8T9t.jpg","eps":[{"id":838316,"url":"http://bgm.tv/ep/838316","type":0,"sort":21,"name":"合体への道のり","name_cn":"","airdate":"2019-06-13","status":"Air"},{"id":890799,"url":"http://bgm.tv/ep/890799","type":0,"sort":22,"name":"","name_cn":"","airdate":"2019-06-20","status":"Today"},{"id":890800,"url":"http://bgm.tv/ep/890800","type":0,"sort":23,"name":"","name_cn":"","airdate":"2019-06-27","status":"NA"}]},
{"id":256561,"name":"なむあみだ仏っ！-蓮台 UTENA-","name_cn":"南无阿弥陀佛！-莲台 UTENA-","air_date":"2019-04-08","weekDayJP":1,"weekDayCN":0,"timeJP":"1900","timeCN":"","image":"http://lain.bgm.tv/pic/cover/g/f7/d7/256561_2I1Pp.jpg","eps":[{"id":874346,"url":"http://bgm.tv/ep/874346","type":0,"sort":10,"name":"","name_cn":"","airdate":"2019-06-10","status":"Air"},{"id":874347,"url":"http://bgm.tv/ep/874347","type":0,"sort":11,"name":"","name_cn":"","airdate":"2019-06-17","status":"Air"},{"id":874348,"url":"http://bgm.tv/ep/874348","type":0,"sort":12,"name":"","name_cn":"","airdate":"2019-06-24","status":"NA"}]},
{"id":247841,"name":"八十亀ちゃんかんさつにっき","name_cn":"八十龟酱观察日记","air_date":"2019-04-04","weekDayJP":4,"weekDayCN":0,"timeJP":"1853","timeCN":"","image":"http://lain.bgm.tv/pic/cover/g/55/38/247841_445ID.jpg","eps":[{"id":874016,"url":"http://bgm.tv/ep/874016","type":0,"sort":11,"name":"","name_cn":"","airdate":"2019-06-13","status":"Air"},{"id":874017,"url":"http://bgm.tv/ep/874017","type":0,"sort":12,"name":"","name_cn":"","airdate":"2019-06-20","status":"Today"}]},
{"id":254762,"name":"文豪ストレイドッグス 第3シーズン","name_cn":"文豪野犬 第三季","air_date":"2019-04-12","weekDayJP":5,"weekDayCN":5,"timeJP":"2130","timeCN":"2130","image":"http://lain.bgm.tv/pic/cover/g/d2/ca/254762_vmbVB.jpg","eps":[{"id":874406,"url":"http://bgm.tv/ep/874406","type":0,"sort":35,"name":"共喰い（其の二）","name_cn":"共噬（其二）","airdate":"2019-06-14","status":"Air"},{"id":874407,"url":"http://bgm.tv/ep/874407","type":0,"sort":36,"name":"共喰い（其の三）","name_cn":"共噬（其三）","airdate":"2019-06-21","status":"NA"},{"id":874408,"url":"http://bgm.tv/ep/874408","type":0,"sort":37,"name":"","name_cn":"","airdate":"2019-06-28","status":"NA"}]},
{"id":193619,"name":"ワンパンマン 第2期","name_cn":"一拳超人 第二季","air_date":"2019-04-02","weekDayJP":3,"weekDayCN":0,"timeJP":"0035","timeCN":"","image":"http://lain.bgm.tv/pic/cover/g/63/0f/193619_MLNLZ.jpg","eps":[{"id":873967,"url":"http://bgm.tv/ep/873967","type":0,"sort":21,"name":"最強の悩み","name_cn":"最强的烦恼","airdate":"2019-06-11","status":"Air"},{"id":873968,"url":"http://bgm.tv/ep/873968","type":0,"sort":22,"name":"正義の包囲網","name_cn":"正义的包围网","airdate":"2019-06-18","status":"Air"},{"id":873969,"url":"http://bgm.tv/ep/873969","type":0,"sort":23,"name":"","name_cn":"","airdate":"2019-06-25","status":"NA"}]},
{"id":267615,"name":"ダイヤのA actⅡ","name_cn":"钻石王牌 act2","air_date":"2019-04-02","weekDayJP":2,"weekDayCN":2,"timeJP":"1655","timeCN":"1830","image":"http://lain.bgm.tv/pic/cover/g/7f/b2/267615_Qio7E.jpg","eps":[{"id":871075,"url":"http://bgm.tv/ep/871075","type":0,"sort":11,"name":"視線の先","name_cn":"视线前方","airdate":"2019-06-11","status":"Air"},{"id":871076,"url":"http://bgm.tv/ep/871076","type":0,"sort":12,"name":"ワガママ","name_cn":"任性","airdate":"2019-06-18","status":"Air"},{"id":871077,"url":"http://bgm.tv/ep/871077","type":0,"sort":13,"name":"","name_cn":"","airdate":"2019-06-25","status":"NA"}]},
{"id":244900,"name":"群青のマグメル","name_cn":"拾又之国","air_date":"2019-04-07","weekDayJP":0,"weekDayCN":0,"timeJP":"2100","timeCN":"","image":"http://lain.bgm.tv/pic/cover/g/6a/3a/244900_i4QTZ.jpg","eps":[{"id":874303,"url":"http://bgm.tv/ep/874303","type":0,"sort":12,"name":"","name_cn":"","airdate":"2019-06-16","status":"Air"}]},
{"id":255667,"name":"八月のシンデレラナイン","name_cn":"八月的灰姑娘棒球队","air_date":"2019-04-07","weekDayJP":1,"weekDayCN":1,"timeJP":"0035","timeCN":"0135","image":"http://lain.bgm.tv/pic/cover/g/15/ac/255667_8xJxj.jpg","eps":[{"id":874264,"url":"http://bgm.tv/ep/874264","type":0,"sort":9,"name":"みんなでつないで、楽しんで","name_cn":"","airdate":"2019-06-16","status":"Air"},{"id":874265,"url":"http://bgm.tv/ep/874265","type":0,"sort":10,"name":"","name_cn":"","airdate":"2019-06-23","status":"NA"}]},
{"id":253048,"name":"ストライクウィッチーズ 501部隊発進しますっ！","name_cn":"强袭魔女 501部队起飞！","air_date":"2019-04-09","weekDayJP":2,"weekDayCN":3,"timeJP":"2345","timeCN":"0000","image":"http://lain.bgm.tv/pic/cover/g/71/f6/253048_38KLC.jpg","eps":[{"id":874370,"url":"http://bgm.tv/ep/874370","type":0,"sort":10,"name":"501夏、感じちゃいます？","name_cn":"501感受到夏天了吗？","airdate":"2019-06-11","status":"Air"},{"id":874371,"url":"http://bgm.tv/ep/874371","type":0,"sort":11,"name":"","name_cn":"","airdate":"2019-06-18","status":"Air"},{"id":874372,"url":"http://bgm.tv/ep/874372","type":0,"sort":12,"name":"","name_cn":"","airdate":"2019-06-25","status":"NA"}]},
{"id":274549,"name":"けだまのゴンじろー","name_cn":"","air_date":"2019-04-06","weekDayJP":6,"weekDayCN":0,"timeJP":"0900","timeCN":"","image":"http://lain.bgm.tv/pic/cover/g/0c/d2/274549_sxB8h.jpg","eps":[{"id":874419,"url":"http://bgm.tv/ep/874419","type":0,"sort":11,"name":"『すげーぞ毛リュウケン』『もうそうがぼうそう？』","name_cn":"","airdate":"2019-06-15","status":"Air"},{"id":874420,"url":"http://bgm.tv/ep/874420","type":0,"sort":12,"name":"","name_cn":"","airdate":"2019-06-22","status":"NA"}]},
{"id":239646,"name":"さらざんまい","name_cn":"皿三昧","air_date":"2019-04-11","weekDayJP":4,"weekDayCN":5,"timeJP":"2355","timeCN":"0325","image":"http://lain.bgm.tv/pic/cover/g/ca/e6/239646_7a46I.jpg","eps":[{"id":872293,"url":"http://bgm.tv/ep/872293","type":0,"sort":10,"name":"つながりたいけど、つながれない","name_cn":"想联系在一起，却无法相连","airdate":"2019-06-13","status":"Air"},{"id":872294,"url":"http://bgm.tv/ep/872294","type":0,"sort":11,"name":"","name_cn":"","airdate":"2019-06-20","status":"Today"}]},
{"id":279468,"name":"爆丸バトルプラネット","name_cn":"","air_date":"2019-04-01","weekDayJP":1,"weekDayCN":0,"timeJP":"1655","timeCN":"","image":"http://lain.bgm.tv/pic/cover/g/14/80/279468_U1kRC.jpg","eps":[{"id":873932,"url":"http://bgm.tv/ep/873932","type":0,"sort":11,"name":"","name_cn":"","airdate":"2019-06-10","status":"Air"},{"id":873933,"url":"http://bgm.tv/ep/873933","type":0,"sort":12,"name":"","name_cn":"","airdate":"2019-06-17","status":"Air"}]},
{"id":255980,"name":"MIX MEISEI STORY","name_cn":"MIX：明青故事","air_date":"2019-04-06","weekDayJP":6,"weekDayCN":6,"timeJP":"1630","timeCN":"1700","image":"http://lain.bgm.tv/pic/cover/g/bd/2f/255980_QS121.jpg","eps":[{"id":874155,"url":"http://bgm.tv/ep/874155","type":0,"sort":11,"name":"投げてみろ","name_cn":"投投看","airdate":"2019-06-15","status":"Air"},{"id":874156,"url":"http://bgm.tv/ep/874156","type":0,"sort":12,"name":"なめてませんか","name_cn":"你在小看我吗","airdate":"2019-06-22","status":"NA"},{"id":877336,"url":"http://bgm.tv/ep/877336","type":0,"sort":13,"name":"","name_cn":"","airdate":"2019-06-29","status":"NA"}]},
{"id":279469,"name":"わしも-wasimo- 第7シリーズ","name_cn":"","air_date":"2019-04-01","weekDayJP":1,"weekDayCN":0,"timeJP":"1700","timeCN":"","image":null,"eps":[{"id":873920,"url":"http://bgm.tv/ep/873920","type":0,"sort":11,"name":"","name_cn":"","airdate":"2019-06-10","status":"Air"},{"id":873921,"url":"http://bgm.tv/ep/873921","type":0,"sort":12,"name":"","name_cn":"","airdate":"2019-06-17","status":"Air"}]},
{"id":279470,"name":"少年アシベ GO!GO!ゴマちゃん 第4シリーズ","name_cn":"少年阿贝GO！GO！小芝麻 第四季","air_date":"2019-04-02","weekDayJP":2,"weekDayCN":2,"timeJP":"1745","timeCN":"2000","image":"http://lain.bgm.tv/pic/cover/g/2c/fb/279470_Ss40J.jpg","eps":[{"id":873942,"url":"http://bgm.tv/ep/873942","type":0,"sort":105,"name":"みんなでケロケロ","name_cn":"大家呱呱呱","airdate":"2019-06-11","status":"Air"},{"id":873943,"url":"http://bgm.tv/ep/873943","type":0,"sort":106,"name":"あさがおを咲かせよう","name_cn":"让牵牛花开","airdate":"2019-06-18","status":"Air"},{"id":873944,"url":"http://bgm.tv/ep/873944","type":0,"sort":107,"name":"夏のおくりもの","name_cn":"","airdate":"2019-06-25","status":"NA"}]},
{"id":269824,"name":"BAKUMATSUクライシス","name_cn":"恋爱幕末男友～于时之彼方盛开之恋～CRISIS","air_date":"2019-04-04","weekDayJP":5,"weekDayCN":0,"timeJP":"0100","timeCN":"","image":"http://lain.bgm.tv/pic/cover/g/72/ec/269824_48U08.jpg","eps":[{"id":874004,"url":"http://bgm.tv/ep/874004","type":0,"sort":11,"name":"","name_cn":"","airdate":"2019-06-13","status":"Air"},{"id":874005,"url":"http://bgm.tv/ep/874005","type":0,"sort":12,"name":"","name_cn":"","airdate":"2019-06-20","status":"Today"}]},
{"id":279471,"name":"ねこねこ日本史 第4シリーズ","name_cn":"猫猫日本史 第四季","air_date":"2019-04-03","weekDayJP":3,"weekDayCN":0,"timeJP":"1745","timeCN":"","image":"http://lain.bgm.tv/pic/cover/g/1d/b1/279471_VB4qr.jpg","eps":[{"id":873980,"url":"http://bgm.tv/ep/873980","type":0,"sort":11,"name":"","name_cn":"","airdate":"2019-06-12","status":"Air"},{"id":873981,"url":"http://bgm.tv/ep/873981","type":0,"sort":12,"name":"","name_cn":"","airdate":"2019-06-19","status":"Air"}]},
{"id":254788,"name":"この音とまれ！","name_cn":"一弦定音！","air_date":"2019-04-06","weekDayJP":0,"weekDayCN":0,"timeJP":"0000","timeCN":"0130","image":"http://lain.bgm.tv/pic/cover/g/17/7f/254788_ai5cE.jpg","eps":[{"id":874167,"url":"http://bgm.tv/ep/874167","type":0,"sort":11,"name":"","name_cn":"","airdate":"2019-06-15","status":"Air"},{"id":874168,"url":"http://bgm.tv/ep/874168","type":0,"sort":12,"name":"","name_cn":"","airdate":"2019-06-22","status":"NA"},{"id":878162,"url":"http://bgm.tv/ep/878162","type":0,"sort":13,"name":"","name_cn":"","airdate":"2019-06-29","status":"NA"}]},
{"id":279472,"name":"妖怪ウォッチ！","name_cn":"妖怪手表！","air_date":"2019-04-05","weekDayJP":5,"weekDayCN":0,"timeJP":"1725","timeCN":"","image":"http://lain.bgm.tv/pic/cover/g/c7/07/279472_g7MOx.jpg","eps":[{"id":874040,"url":"http://bgm.tv/ep/874040","type":0,"sort":11,"name":"妖怪おすべり様／ドクターＦ　＃1／４コマさん「バス」／ニッポン全国 コマみ探しの旅！ 恐山編","name_cn":"","airdate":"2019-06-14","status":"Air"},{"id":874041,"url":"http://bgm.tv/ep/874041","type":0,"sort":12,"name":"","name_cn":"","airdate":"2019-06-21","status":"NA"}]},
{"id":279473,"name":"あはれ！名作くん 第4期","name_cn":"做得很好！名作君 第四季","air_date":"2019-04-05","weekDayJP":5,"weekDayCN":0,"timeJP":"1720","timeCN":"","image":"http://lain.bgm.tv/pic/cover/g/f9/98/279473_uu6FQ.jpg","eps":[{"id":874028,"url":"http://bgm.tv/ep/874028","type":0,"sort":11,"name":"","name_cn":"","airdate":"2019-06-14","status":"Air"},{"id":874029,"url":"http://bgm.tv/ep/874029","type":0,"sort":12,"name":"","name_cn":"","airdate":"2019-06-21","status":"NA"}]},
{"id":279474,"name":"デュエル・マスターズ!!","name_cn":"决斗大师！！","air_date":"2019-04-07","weekDayJP":0,"weekDayCN":0,"timeJP":"0730","timeCN":"","image":null,"eps":[{"id":874179,"url":"http://bgm.tv/ep/874179","type":0,"sort":11,"name":"","name_cn":"","airdate":"2019-06-16","status":"Air"},{"id":874180,"url":"http://bgm.tv/ep/874180","type":0,"sort":12,"name":"","name_cn":"","airdate":"2019-06-23","status":"NA"}]},
{"id":239912,"name":"キャロル＆チューズデイ","name_cn":"CAROLE &amp; TUESDAY","air_date":"2019-04-10","weekDayJP":4,"weekDayCN":4,"timeJP":"0005","timeCN":"0430","image":"http://lain.bgm.tv/pic/cover/g/50/aa/239912_z34n4.jpg","eps":[{"id":872304,"url":"http://bgm.tv/ep/872304","type":0,"sort":10,"name":"River Deep, Mountain High","name_cn":"山高水深","airdate":"2019-06-12","status":"Air"},{"id":872305,"url":"http://bgm.tv/ep/872305","type":0,"sort":11,"name":"With or Without You","name_cn":"有或没有你","airdate":"2019-06-19","status":"Air"},{"id":872306,"url":"http://bgm.tv/ep/872306","type":0,"sort":12,"name":"","name_cn":"","airdate":"2019-06-26","status":"NA"}]},
{"id":279475,"name":"テレビ野郎 ナナーナ　わくわく洞窟ランド","name_cn":"香蕉怪大叔 呐呐~呐 好奇洞穴乐园","air_date":"2019-04-11","weekDayJP":5,"weekDayCN":4,"timeJP":"0000","timeCN":"1953","image":"http://lain.bgm.tv/pic/cover/g/d8/a5/279475_MUdAu.jpg","eps":[{"id":874394,"url":"http://bgm.tv/ep/874394","type":0,"sort":10,"name":"","name_cn":"","airdate":"2019-06-13","status":"Air"},{"id":874395,"url":"http://bgm.tv/ep/874395","type":0,"sort":11,"name":"","name_cn":"","airdate":"2019-06-20","status":"Today"},{"id":874396,"url":"http://bgm.tv/ep/874396","type":0,"sort":12,"name":"","name_cn":"","airdate":"2019-06-27","status":"NA"}]},
{"id":250724,"name":"真夜中のオカルト公務員","name_cn":"深夜的超自然公务员","air_date":"2019-04-07","weekDayJP":0,"weekDayCN":0,"timeJP":"2330","timeCN":"2330","image":"http://lain.bgm.tv/pic/cover/g/8e/68/250724_053c1.jpg","eps":[{"id":874278,"url":"http://bgm.tv/ep/874278","type":0,"sort":11,"name":"砂の耳と新人の根性","name_cn":"","airdate":"2019-06-16","status":"Air"},{"id":874279,"url":"http://bgm.tv/ep/874279","type":0,"sort":12,"name":"","name_cn":"","airdate":"2019-06-23","status":"NA"}]},
{"id":263750,"name":"進撃の巨人 Season 3 Part.2","name_cn":"进击的巨人 第三季 Part.2","air_date":"2019-04-28","weekDayJP":0,"weekDayCN":1,"timeJP":"2310","timeCN":"0140","image":"http://lain.bgm.tv/pic/cover/g/c2/56/263750_HBbTh.jpg","eps":[{"id":792622,"url":"http://bgm.tv/ep/792622","type":0,"sort":57,"name":"あの日","name_cn":"那一天","airdate":"2019-06-16","status":"Air"},{"id":792623,"url":"http://bgm.tv/ep/792623","type":0,"sort":58,"name":"進撃の巨人","name_cn":"进击的巨人","airdate":"2019-06-23","status":"NA"}]},
{"id":267412,"name":"機動戦士ガンダム THE ORIGIN 前夜 赤い彗星","name_cn":"机动战士高达 THE ORIGIN 前夜 红色彗星","air_date":"2019-04-29","weekDayJP":0,"weekDayCN":0,"timeJP":"2335","timeCN":"","image":"http://lain.bgm.tv/pic/cover/g/4f/e2/267412_XsOB3.jpg","eps":[{"id":842447,"url":"http://bgm.tv/ep/842447","type":0,"sort":7,"name":"","name_cn":"","airdate":"2019-06-10","status":"Air"},{"id":842448,"url":"http://bgm.tv/ep/842448","type":0,"sort":8,"name":"","name_cn":"","airdate":"2019-06-17","status":"Air"},{"id":842449,"url":"http://bgm.tv/ep/842449","type":0,"sort":9,"name":"","name_cn":"","airdate":"2019-06-24","status":"NA"}]}]